simple_spider/__init__.py
simple_spider/base_spider.py
simple_spider/fetcher.py
simple_spider/proxy.py
simple_spider/utils.py
simple_spider-1.3.19.dist-info/METADATA
simple_spider-1.3.19.dist-info/RECORD
simple_spider-1.3.19.dist-info/WHEEL
simple_spider-1.3.19.dist-info/top_level.txt
