Metadata-Version: 2.1
Name: simple-spider
Version: 1.3.19
Summary: simple spider framework
Home-page: https://www.typechodev.com
Author: leimiu
Author-email: miuyin@126.com
License: Apache Software License
Platform: UNKNOWN
Classifier: Development Status :: 5 - Production/Stable
Classifier: Intended Audience :: Developers
Classifier: Topic :: Software Development :: Build Tools
Classifier: License :: OSI Approved :: MIT License
Classifier: Programming Language :: Python :: 3
Requires-Dist: requests[socks]
Requires-Dist: pymongo
Requires-Dist: pyquery
Requires-Dist: redis
Requires-Dist: simplejson
Requires-Dist: tomd
Requires-Dist: markdown
